sermatec_inverter/__init__.py
sermatec_inverter/__main__.py
sermatec_inverter-2022.3.dist-info/METADATA
sermatec_inverter-2022.3.dist-info/WHEEL
sermatec_inverter-2022.3.dist-info/licenses/LICENSE
sermatec_inverter-2022.3.dist-info/RECORD
