Metadata-Version: 2.1
Name: sermatec-inverter
Version: 2022.3
Summary: Sermatec Solar Inverter communication script
Project-URL: Homepage, https://github.com/andreondra/sermatec-inverter
Project-URL: Bug Tracker, https://github.com/andreondra/sermatec-inverter/issues
Author-email: Ondrej Golasowski <golasowski.o@gmail.com>
License: MIT License
License-File: LICENSE
Classifier: License :: OSI Approved :: MIT License
Classifier: Operating System :: OS Independent
Classifier: Programming Language :: Python :: 3
Requires-Python: >=3.7
